{
  "sections": {
    "main": {
      "type": "main-page",
      "disabled": true,
      "settings": {
      }
    },
    "rich_text_9YTrrX": {
      "type": "rich-text",
      "blocks": {
        "text_DGatGC": {
          "type": "text",
          "settings": {
            "enlarge_text": true,
            "text": "<p>A day on the river with a professional guide from St. Peter’s is designed to maximize your enjoyment. All guide trips are tailored to the instructional needs of each individual. Each trip will build fundamental fly fishing skills, expand your understanding of local rivers and help perfect your fly presentation.  We are ready and willing to provide comprehensive instruction on casting, bug selection, rigging and fly fishing techniques.  Our overall goal is to increase your fly fishing knowledge and skills, all while having a pleasurable experience on the water.<\/p><p>Below you will find detailed information on what to expect during a St. Peter's guide trip, pricing for the various opportunities we offer, and details on our unique rental program.<\/p>"
          }
        }
      },
      "block_order": [
        "text_DGatGC"
      ],
      "settings": {
        "align_text": "center",
        "narrow_column": true,
        "divider": false
      }
    },
    "slideshow_YN9FcH": {
      "type": "slideshow",
      "blocks": {
        "image_aRfyPh": {
          "type": "image",
          "settings": {
            "title": "The Experience",
            "title_size": 80,
            "subheading": "",
            "link": "",
            "link_text": "",
            "text_align": "vertical-bottom horizontal-left",
            "image": "shopify:\/\/shop_images\/upper_ppoudre.jpg",
            "parallax_direction": "top",
            "overlay_opacity": 0
          }
        },
        "image_BYhdmK": {
          "type": "image",
          "settings": {
            "title": "",
            "title_size": 80,
            "subheading": "",
            "link": "",
            "link_text": "",
            "text_align": "vertical-bottom horizontal-left",
            "image": "shopify:\/\/shop_images\/IMG_6169.webp",
            "parallax_direction": "top",
            "overlay_opacity": 0
          }
        }
      },
      "block_order": [
        "image_aRfyPh",
        "image_BYhdmK"
      ],
      "settings": {
        "section_height": "650px",
        "mobile_height": "auto",
        "parallax": true,
        "style": "arrows",
        "autoplay": true,
        "autoplay_speed": 5,
        "lazyload_images": true
      }
    },
    "rich_text_XXNGPy": {
      "type": "rich-text",
      "blocks": {
        "text_jrB46D": {
          "type": "text",
          "settings": {
            "enlarge_text": true,
            "text": "<p>Your day on the river with a guide from St. Peter's Fly Shop is designed to maximize your enjoyment. All guide trips can be instructional...or we can just go out and help you catch fish. Part school, part fishing, our trips will build your fundamental fly fishing skills, expand your understanding of local entomology, work the kinks out of your presentation, or help you get rid of that annoying tailing loop. Let us know what we can do to maximize your enjoyment on stream and we'll do whatever we can to accommodate you.<\/p><p>Our guide trips include everything you'll need for your day on stream. We are pleased to provide our clients with the fine rods from the Sage Manufacturing and Scott Fly Rod Company. Our reels and lines come from leading manufacturers in the industry such as Waterworks Lamson, Hatch Reels and Ross Reels, Scientific Anglers, Rio Products. Wading equipment can be provided upon request.<\/p><p>Our full day float and wade trips include lunch and beverages on stream. Drinks and snacks are provided on half day trips. Do you have dietary restrictions or other special needs? Please let us know and we're happy to accommodate you.<\/p>"
          }
        }
      },
      "block_order": [
        "text_jrB46D"
      ],
      "settings": {
        "align_text": "center",
        "narrow_column": true,
        "divider": false
      }
    },
    "advanced_content_BCfVCA": {
      "type": "advanced-content",
      "blocks": {
        "image_xFzWyG": {
          "type": "image",
          "settings": {
            "image": "shopify:\/\/shop_images\/group_ic.jpg",
            "link": "shopify:\/\/blogs\/guide-service\/meet-our-guides",
            "width": "50%",
            "alignment": "center"
          }
        },
        "liquid_b4yPnG": {
          "type": "liquid",
          "settings": {
            "code": "<h2>Our Guides<\/h2><p>Here at St. Peter's we strive to provide our clients with friendly, knowledgeable, well trained guides who's primary focus is you. There are plenty of shops out there willing to match you up with a warm body that's basically getting paid to learn the water and take you along. Not here...\nOur guides are experienced fly fishers with extensive knowledge of local streams, hatches, and techniques. While we've got our share of eccentrics on staff, you will not find attitudes, assumptions, or criticisms from our guides. If you do, we want to hear about it.<\/p>",
            "width": "50%",
            "alignment": "center"
          }
        }
      },
      "block_order": [
        "image_xFzWyG",
        "liquid_b4yPnG"
      ],
      "settings": {
        "full_width": false,
        "space_around": true,
        "lazyload_images": true
      }
    },
    "rich_text_wYkmjk": {
      "type": "rich-text",
      "blocks": {
        "heading_PQitft": {
          "type": "heading",
          "settings": {
            "title": "What to Bring?"
          }
        },
        "text_tktiD3": {
          "type": "text",
          "settings": {
            "enlarge_text": true,
            "text": "<p>Bring any of your own equipment that you would like to use. We have waders, boots, rods and reels available for all our clients going on a guided fishing trip with us.<\/p><p>Light Jacket \/ Rain Jacket  -  Polarized Sunglasses  -  Hat with brim  -  Sunscreen  -  Socks<\/p>"
          }
        }
      },
      "block_order": [
        "heading_PQitft",
        "text_tktiD3"
      ],
      "settings": {
        "align_text": "center",
        "narrow_column": true,
        "divider": false
      }
    },
    "rich_text_GYqf8j": {
      "type": "rich-text",
      "blocks": {
        "heading_dGGqDb": {
          "type": "heading",
          "settings": {
            "title": "Pricing"
          }
        },
        "text_yzFU9P": {
          "type": "text",
          "settings": {
            "enlarge_text": true,
            "text": "<h3>Walk-Wade Trips<\/h3><h3>Cache La Poudre - Big Thompson - Rocky Mountain National Park - North Park<\/h3><p><strong>1 Angler<\/strong>----------$350   <strong>Half Day<\/strong>     $450  <strong>Full Day<\/strong><\/p><p><strong>2 Anglers<\/strong>----------$450  <strong>Half Day <\/strong>    $550  <strong>Full Day<\/strong><\/p><p><strong>3 Anglers<\/strong>----------$550  <strong>Half Day<\/strong>     $650  <strong>Full Day<\/strong><\/p><p><strong>Upper North Platte Canyon and North Park*<\/strong> Walk\/Wade-----------<strong>Full Day Only<\/strong><\/p><p><strong>1 Angler<\/strong>----------$500<\/p><p><strong>2 Anglers<\/strong>----------$600<\/p><p>*Additional rod fee for private water on North Park waters<\/p><h1><strong> Float Trips<br\/><\/strong><\/h1><h3>Grey Reef - Miracle Mile - Upper North Platte - Encampment - Cache La Poudre<\/h3><p><strong>Grey Reef (April-October)<\/strong>----------$600<\/p><p><strong>Grey Reef (Nov-March)<\/strong>----------$500<\/p><p><strong>Miracle Mile (April-October)<\/strong>----------$650<\/p><p><strong>Miracle Mile (Nov-March)<\/strong>----------$550<\/p><p><strong>Upper North Platte (Saratoga\/Treasure Island area) & Encampment<\/strong>----------$700<\/p><p><strong>Upper North Platte (Northgate area)<\/strong>----------$750<\/p><p><strong>Cache La Poudre<\/strong> (Half Day)----------$500<\/p><p>-Float trip prices are for one boat with 2 anglers per boat.<\/p><p><strong>ALL TRIPS INCLUDE GEAR, FLIES, BEVERAGES & SNACKS, FULL DAY TRIPS INCLUDE LUNCH<\/strong><\/p><p><strong>GRATUITY & FISHING LICENSE NOT INCLUDED IN COST<\/strong><\/p><h4>*A deposit is required for booking.  All deposits are refundable, minus the 5% cancellation fee, up to 30 days prior to your trip.  All cancellations within 30 days of trip are subject to forfeiture of deposit. Health and medical issues do not change the cancellation policy. If you have any concern about the need to cancel, we recommend you purchase trip insurance to cover costs.*<\/h4>"
          }
        },
        "text_kmMkgy": {
          "type": "text",
          "settings": {
            "enlarge_text": true,
            "text": "<h3><strong>Rod, Reel, Spey Line, Waders, and Boots:  Each Item $15.00 per day*<\/strong><\/h3><h3><strong>Spey Rod\/Reel\/Line Combo: $25\/Day*<\/strong><\/h3><p>*A one-time $30 credit is available for 60 days after original rental and can be applied to a future purchase of \"like\" item<strong>.<\/strong> <\/p><p>Ask store employee for details.<\/p><p>St. Peter's Fly Shop LLC is an equal opportunity service provider and employer including individuals with disabilities, operating under permit from the Medicine Bow-Routt National Forests, the Arapahoe-Roosevelt National Forests, and Bureau of Land Management.  St. Peter's Fly Shop is a registered Colorado Outfitter #2420.<\/p>"
          }
        }
      },
      "block_order": [
        "heading_dGGqDb",
        "text_yzFU9P",
        "text_kmMkgy"
      ],
      "settings": {
        "align_text": "center",
        "narrow_column": true,
        "divider": false
      }
    }
  },
  "order": [
    "main",
    "rich_text_9YTrrX",
    "slideshow_YN9FcH",
    "rich_text_XXNGPy",
    "advanced_content_BCfVCA",
    "rich_text_wYkmjk",
    "rich_text_GYqf8j"
  ]
}
